[
  {
    "type": "net_read_primitive",
    "method_name": "ReadString",
    "raw_args": "",
    "message_name": "adminSpawnItem",
    "message_direction": "Receive",
    "context_confidence": "medium",
    "file": "plugins\\adminspawnmenu.lua",
    "line": 12,
    "realm": "unknown",
    "framework_layer": "domain"
  },
  {
    "type": "net_read_entity_ref",
    "method_name": "ReadEntity",
    "raw_args": "",
    "message_name": "OpenCustomItemMenu",
    "message_direction": "Start",
    "context_confidence": "medium",
    "file": "plugins\\admintools\\sh_plugin.lua",
    "line": 862,
    "realm": "shared",
    "framework_layer": "domain"
  },
  {
    "type": "net_read_entity_ref",
    "method_name": "ReadEntity",
    "raw_args": "",
    "message_name": "OpenCustomItemMenu",
    "message_direction": "Start",
    "context_confidence": "medium",
    "file": "plugins\\admintools\\sh_plugin.lua",
    "line": 886,
    "realm": "shared",
    "framework_layer": "domain"
  },
  {
    "type": "net_read_other",
    "method_name": "ReadVector",
    "raw_args": "",
    "message_name": "RemoveItem",
    "message_direction": "Receive",
    "context_confidence": "medium",
    "file": "plugins\\admintools\\sv_hooks.lua",
    "line": 91,
    "realm": "server",
    "framework_layer": "domain"
  },
  {
    "type": "net_read_primitive",
    "method_name": "ReadUInt",
    "raw_args": "6",
    "message_name": "ShowScreamerImage",
    "message_direction": "Receive",
    "context_confidence": "medium",
    "file": "plugins\\biorezonance\\sh_plugin.lua",
    "line": 280,
    "realm": "shared",
    "framework_layer": "domain"
  },
  {
    "type": "net_read_primitive",
    "method_name": "ReadUInt",
    "raw_args": "6",
    "message_name": "ShowScreamerImage2",
    "message_direction": "Receive",
    "context_confidence": "medium",
    "file": "plugins\\biorezonance\\sh_plugin.lua",
    "line": 317,
    "realm": "shared",
    "framework_layer": "domain"
  },
  {
    "type": "net_read_primitive",
    "method_name": "ReadBool",
    "raw_args": "",
    "message_name": "ShowScreamerImage2",
    "message_direction": "Receive",
    "context_confidence": "medium",
    "file": "plugins\\biorezonance\\sh_plugin.lua",
    "line": 318,
    "realm": "shared",
    "framework_layer": "domain"
  },
  {
    "type": "net_read_other",
    "method_name": "ReadType",
    "raw_args": "",
    "message_name": "cOpen",
    "message_direction": "Receive",
    "context_confidence": "medium",
    "file": "plugins\\cassetteplayer\\sh_plugin.lua",
    "line": 21,
    "realm": "shared",
    "framework_layer": "domain"
  },
  {
    "type": "net_read_primitive",
    "method_name": "ReadUInt",
    "raw_args": "32",
    "message_name": "cOpen",
    "message_direction": "Receive",
    "context_confidence": "medium",
    "file": "plugins\\cassetteplayer\\sh_plugin.lua",
    "line": 22,
    "realm": "shared",
    "framework_layer": "domain"
  },
  {
    "type": "net_read_primitive",
    "method_name": "ReadString",
    "raw_args": "",
    "message_name": "StartCraft",
    "message_direction": "Receive",
    "context_confidence": "medium",
    "file": "plugins\\crafting\\sh_plugin.lua",
    "line": 18,
    "realm": "shared",
    "framework_layer": "domain"
  },
  {
    "type": "net_read_entity_ref",
    "method_name": "ReadEntity",
    "raw_args": "",
    "message_name": "StartCraft",
    "message_direction": "Receive",
    "context_confidence": "medium",
    "file": "plugins\\crafting\\sh_plugin.lua",
    "line": 19,
    "realm": "shared",
    "framework_layer": "domain"
  },
  {
    "type": "net_read_primitive",
    "method_name": "ReadString",
    "raw_args": "",
    "message_name": "OpenCraft",
    "message_direction": "Receive",
    "context_confidence": "medium",
    "file": "plugins\\crafting\\sh_plugin.lua",
    "line": 286,
    "realm": "shared",
    "framework_layer": "domain"
  },
  {
    "type": "net_read_primitive",
    "method_name": "ReadString",
    "raw_args": "",
    "message_name": "OpenCraft",
    "message_direction": "Receive",
    "context_confidence": "medium",
    "file": "plugins\\crafting\\sh_plugin.lua",
    "line": 287,
    "realm": "shared",
    "framework_layer": "domain"
  },
  {
    "type": "net_read_entity_ref",
    "method_name": "ReadEntity",
    "raw_args": "",
    "message_name": "OpenCraft",
    "message_direction": "Receive",
    "context_confidence": "medium",
    "file": "plugins\\crafting\\sh_plugin.lua",
    "line": 288,
    "realm": "shared",
    "framework_layer": "domain"
  },
  {
    "type": "net_read_primitive",
    "method_name": "ReadInt",
    "raw_args": "32",
    "message_name": "hackent",
    "message_direction": "Receive",
    "context_confidence": "medium",
    "file": "plugins\\hacking\\sh_plugin.lua",
    "line": 475,
    "realm": "shared",
    "framework_layer": "domain"
  },
  {
    "type": "net_read_primitive",
    "method_name": "ReadString",
    "raw_args": "",
    "message_name": "hackent",
    "message_direction": "Receive",
    "context_confidence": "medium",
    "file": "plugins\\hacking\\sh_plugin.lua",
    "line": 476,
    "realm": "shared",
    "framework_layer": "domain"
  },
  {
    "type": "net_read_primitive",
    "method_name": "ReadInt",
    "raw_args": "32",
    "message_name": "hackfail",
    "message_direction": "Receive",
    "context_confidence": "medium",
    "file": "plugins\\hacking\\sh_plugin.lua",
    "line": 481,
    "realm": "shared",
    "framework_layer": "domain"
  },
  {
    "type": "net_read_primitive",
    "method_name": "ReadString",
    "raw_args": "",
    "message_name": "hackfail",
    "message_direction": "Receive",
    "context_confidence": "medium",
    "file": "plugins\\hacking\\sh_plugin.lua",
    "line": 482,
    "realm": "shared",
    "framework_layer": "domain"
  },
  {
    "type": "net_read_complex_or_bulk",
    "method_name": "ReadTable",
    "raw_args": "",
    "message_name": "givenearbyents",
    "message_direction": "Receive",
    "context_confidence": "medium",
    "file": "plugins\\hacking\\sh_plugin.lua",
    "line": 676,
    "realm": "shared",
    "framework_layer": "domain"
  },
  {
    "type": "net_read_primitive",
    "method_name": "ReadInt",
    "raw_args": "32",
    "message_name": "RandomNumber",
    "message_direction": "Receive",
    "context_confidence": "medium",
    "file": "plugins\\lightitems\\cl_hooks.lua",
    "line": 6,
    "realm": "client",
    "framework_layer": "domain"
  },
  {
    "type": "net_read_primitive",
    "method_name": "ReadInt",
    "raw_args": "32",
    "message_name": "RandomNumber",
    "message_direction": "Receive",
    "context_confidence": "medium",
    "file": "plugins\\lightitems\\cl_hooks.lua",
    "line": 7,
    "realm": "client",
    "framework_layer": "domain"
  },
  {
    "type": "net_read_complex_or_bulk",
    "method_name": "ReadTable",
    "raw_args": "",
    "message_name": "SendItemData",
    "message_direction": "Receive",
    "context_confidence": "medium",
    "file": "plugins\\admintools\\derma\\cl_itempanel.lua",
    "line": 24,
    "realm": "client",
    "framework_layer": "domain"
  },
  {
    "type": "net_read_complex_or_bulk",
    "method_name": "ReadTable",
    "raw_args": "",
    "message_name": "SendEntityData",
    "message_direction": "Receive",
    "context_confidence": "medium",
    "file": "plugins\\admintools\\derma\\cl_itempanel.lua",
    "line": 47,
    "realm": "client",
    "framework_layer": "domain"
  },
  {
    "type": "net_read_primitive",
    "method_name": "ReadString",
    "raw_args": "",
    "message_name": "ItemFound",
    "message_direction": "Receive",
    "context_confidence": "medium",
    "file": "plugins\\lootablecontainers\\entities\\entities\\nut_loot_junk\\cl_init.lua",
    "line": 4,
    "realm": "client",
    "framework_layer": "domain"
  },
  {
    "type": "net_read_entity_ref",
    "method_name": "ReadEntity",
    "raw_args": "",
    "message_name": "CreedBroomSweep2",
    "message_direction": "Receive",
    "context_confidence": "medium",
    "file": "plugins\\newweapons\\entities\\weapons\\nut_mop.lua",
    "line": 18,
    "realm": "unknown",
    "framework_layer": "domain"
  },
  {
    "type": "net_read_primitive",
    "method_name": "ReadUInt",
    "raw_args": "32",
    "message_name": "nutCorpseTransfer",
    "message_direction": "Receive",
    "context_confidence": "medium",
    "file": "plugins\\ragdollinteraction\\interaction\\sv_networking.lua",
    "line": 14,
    "realm": "server",
    "framework_layer": "domain"
  },
  {
    "type": "net_read_entity_ref",
    "method_name": "ReadEntity",
    "raw_args": "",
    "message_name": null,
    "message_direction": null,
    "context_confidence": "low",
    "file": "plugins\\persistence.lua",
    "line": 49,
    "realm": "unknown",
    "framework_layer": "framework"
  },
  {
    "type": "net_read_entity_ref",
    "method_name": "ReadEntity",
    "raw_args": "",
    "message_name": null,
    "message_direction": null,
    "context_confidence": "low",
    "file": "plugins\\persistence.lua",
    "line": 88,
    "realm": "unknown",
    "framework_layer": "framework"
  },
  {
    "type": "net_read_primitive",
    "method_name": "ReadString",
    "raw_args": "",
    "message_name": "nutPluginDisable",
    "message_direction": "Receive",
    "context_confidence": "medium",
    "file": "plugins\\pluginconfig.lua",
    "line": 83,
    "realm": "unknown",
    "framework_layer": "framework"
  },
  {
    "type": "net_read_other",
    "method_name": "ReadBit",
    "raw_args": "",
    "message_name": "nutPluginDisable",
    "message_direction": "Receive",
    "context_confidence": "medium",
    "file": "plugins\\pluginconfig.lua",
    "line": 84,
    "realm": "unknown",
    "framework_layer": "framework"
  },
  {
    "type": "net_read_primitive",
    "method_name": "ReadUInt",
    "raw_args": "32",
    "message_name": "nutPluginList",
    "message_direction": "Receive",
    "context_confidence": "medium",
    "file": "plugins\\pluginconfig.lua",
    "line": 176,
    "realm": "unknown",
    "framework_layer": "framework"
  },
  {
    "type": "net_read_primitive",
    "method_name": "ReadString",
    "raw_args": "",
    "message_name": "nutPluginList",
    "message_direction": "Receive",
    "context_confidence": "medium",
    "file": "plugins\\pluginconfig.lua",
    "line": 179,
    "realm": "unknown",
    "framework_layer": "framework"
  },
  {
    "type": "net_read_other",
    "method_name": "ReadBit",
    "raw_args": "",
    "message_name": "nutPluginList",
    "message_direction": "Receive",
    "context_confidence": "medium",
    "file": "plugins\\pluginconfig.lua",
    "line": 179,
    "realm": "unknown",
    "framework_layer": "framework"
  },
  {
    "type": "net_read_primitive",
    "method_name": "ReadString",
    "raw_args": "",
    "message_name": "nutPluginDisable",
    "message_direction": "Receive",
    "context_confidence": "medium",
    "file": "plugins\\pluginconfig.lua",
    "line": 185,
    "realm": "unknown",
    "framework_layer": "framework"
  },
  {
    "type": "net_read_other",
    "method_name": "ReadBit",
    "raw_args": "",
    "message_name": "nutPluginDisable",
    "message_direction": "Receive",
    "context_confidence": "medium",
    "file": "plugins\\pluginconfig.lua",
    "line": 186,
    "realm": "unknown",
    "framework_layer": "framework"
  },
  {
    "type": "net_read_primitive",
    "method_name": "ReadBool",
    "raw_args": "",
    "message_name": "nutTypeStatus",
    "message_direction": "Receive",
    "context_confidence": "medium",
    "file": "plugins\\typing.lua",
    "line": 66,
    "realm": "unknown",
    "framework_layer": "framework"
  },
  {
    "type": "net_read_entity_ref",
    "method_name": "ReadEntity",
    "raw_args": "",
    "message_name": "VManip_PickupEntity",
    "message_direction": "Receive",
    "context_confidence": "medium",
    "file": "gamemode\\core\\hooks\\sv_hooks.lua",
    "line": 900,
    "realm": "server",
    "framework_layer": "framework"
  },
  {
    "type": "net_read_primitive",
    "method_name": "ReadString",
    "raw_args": "",
    "message_name": "syncClientTime",
    "message_direction": "Receive",
    "context_confidence": "medium",
    "file": "gamemode\\core\\libs\\sh_date.lua",
    "line": 157,
    "realm": "shared",
    "framework_layer": "framework"
  },
  {
    "type": "net_read_primitive",
    "method_name": "ReadString",
    "raw_args": "",
    "message_name": "nutNotify",
    "message_direction": "Receive",
    "context_confidence": "medium",
    "file": "gamemode\\core\\util\\cl_notice.lua",
    "line": 12,
    "realm": "client",
    "framework_layer": "framework"
  },
  {
    "type": "net_read_primitive",
    "method_name": "ReadString",
    "raw_args": "",
    "message_name": "nutNotifyL",
    "message_direction": "Receive",
    "context_confidence": "medium",
    "file": "gamemode\\core\\util\\cl_notice.lua",
    "line": 17,
    "realm": "client",
    "framework_layer": "framework"
  },
  {
    "type": "net_read_primitive",
    "method_name": "ReadUInt",
    "raw_args": "8",
    "message_name": "nutNotifyL",
    "message_direction": "Receive",
    "context_confidence": "medium",
    "file": "gamemode\\core\\util\\cl_notice.lua",
    "line": 18,
    "realm": "client",
    "framework_layer": "framework"
  },
  {
    "type": "net_read_primitive",
    "method_name": "ReadString",
    "raw_args": "",
    "message_name": "nutNotifyL",
    "message_direction": "Receive",
    "context_confidence": "medium",
    "file": "gamemode\\core\\util\\cl_notice.lua",
    "line": 26,
    "realm": "client",
    "framework_layer": "framework"
  },
  {
    "type": "net_read_primitive",
    "method_name": "ReadUInt",
    "raw_args": "32",
    "message_name": "nutStringReq",
    "message_direction": "Receive",
    "context_confidence": "medium",
    "file": "gamemode\\core\\util\\cl_stringreq.lua",
    "line": 2,
    "realm": "client",
    "framework_layer": "framework"
  },
  {
    "type": "net_read_primitive",
    "method_name": "ReadString",
    "raw_args": "",
    "message_name": "nutStringReq",
    "message_direction": "Receive",
    "context_confidence": "medium",
    "file": "gamemode\\core\\util\\cl_stringreq.lua",
    "line": 3,
    "realm": "client",
    "framework_layer": "framework"
  },
  {
    "type": "net_read_primitive",
    "method_name": "ReadString",
    "raw_args": "",
    "message_name": "nutStringReq",
    "message_direction": "Receive",
    "context_confidence": "medium",
    "file": "gamemode\\core\\util\\cl_stringreq.lua",
    "line": 4,
    "realm": "client",
    "framework_layer": "framework"
  },
  {
    "type": "net_read_primitive",
    "method_name": "ReadString",
    "raw_args": "",
    "message_name": "nutStringReq",
    "message_direction": "Receive",
    "context_confidence": "medium",
    "file": "gamemode\\core\\util\\cl_stringreq.lua",
    "line": 5,
    "realm": "client",
    "framework_layer": "framework"
  },
  {
    "type": "net_read_primitive",
    "method_name": "ReadUInt",
    "raw_args": "32",
    "message_name": "nutStringReq",
    "message_direction": "Receive",
    "context_confidence": "medium",
    "file": "gamemode\\core\\util\\sv_stringreq.lua",
    "line": 31,
    "realm": "server",
    "framework_layer": "framework"
  },
  {
    "type": "net_read_primitive",
    "method_name": "ReadString",
    "raw_args": "",
    "message_name": "nutStringReq",
    "message_direction": "Receive",
    "context_confidence": "medium",
    "file": "gamemode\\core\\util\\sv_stringreq.lua",
    "line": 32,
    "realm": "server",
    "framework_layer": "framework"
  },
  {
    "type": "net_read_primitive",
    "method_name": "ReadUInt",
    "raw_args": "32",
    "message_name": "nutItemInstance",
    "message_direction": "Receive",
    "context_confidence": "medium",
    "file": "gamemode\\core\\libs\\item\\cl_networking.lua",
    "line": 36,
    "realm": "client",
    "framework_layer": "framework"
  },
  {
    "type": "net_read_primitive",
    "method_name": "ReadString",
    "raw_args": "",
    "message_name": "nutItemInstance",
    "message_direction": "Receive",
    "context_confidence": "medium",
    "file": "gamemode\\core\\libs\\item\\cl_networking.lua",
    "line": 37,
    "realm": "client",
    "framework_layer": "framework"
  },
  {
    "type": "net_read_complex_or_bulk",
    "method_name": "ReadTable",
    "raw_args": "",
    "message_name": "nutItemInstance",
    "message_direction": "Receive",
    "context_confidence": "medium",
    "file": "gamemode\\core\\libs\\item\\cl_networking.lua",
    "line": 38,
    "realm": "client",
    "framework_layer": "framework"
  },
  {
    "type": "net_read_other",
    "method_name": "ReadType",
    "raw_args": "",
    "message_name": "nutItemInstance",
    "message_direction": "Receive",
    "context_confidence": "medium",
    "file": "gamemode\\core\\libs\\item\\cl_networking.lua",
    "line": 40,
    "realm": "client",
    "framework_layer": "framework"
  },
  {
    "type": "net_read_primitive",
    "method_name": "ReadUInt",
    "raw_args": "32",
    "message_name": "nutItemInstance",
    "message_direction": "Receive",
    "context_confidence": "medium",
    "file": "gamemode\\core\\libs\\item\\cl_networking.lua",
    "line": 41,
    "realm": "client",
    "framework_layer": "framework"
  },
  {
    "type": "net_read_primitive",
    "method_name": "ReadUInt",
    "raw_args": "32",
    "message_name": "nutCharacterInvList",
    "message_direction": "Receive",
    "context_confidence": "medium",
    "file": "gamemode\\core\\libs\\item\\cl_networking.lua",
    "line": 52,
    "realm": "client",
    "framework_layer": "framework"
  },
  {
    "type": "net_read_primitive",
    "method_name": "ReadUInt",
    "raw_args": "32",
    "message_name": "nutCharacterInvList",
    "message_direction": "Receive",
    "context_confidence": "medium",
    "file": "gamemode\\core\\libs\\item\\cl_networking.lua",
    "line": 53,
    "realm": "client",
    "framework_layer": "framework"
  },
  {
    "type": "net_read_other",
    "method_name": "ReadType",
    "raw_args": "",
    "message_name": "nutCharacterInvList",
    "message_direction": "Receive",
    "context_confidence": "medium",
    "file": "gamemode\\core\\libs\\item\\cl_networking.lua",
    "line": 57,
    "realm": "client",
    "framework_layer": "framework"
  },
  {
    "type": "net_read_primitive",
    "method_name": "ReadUInt",
    "raw_args": "32",
    "message_name": "nutItemDelete",
    "message_direction": "Receive",
    "context_confidence": "medium",
    "file": "gamemode\\core\\libs\\item\\cl_networking.lua",
    "line": 67,
    "realm": "client",
    "framework_layer": "framework"
  },
  {
    "type": "net_read_primitive",
    "method_name": "ReadString",
    "raw_args": "",
    "message_name": "NetStreamDS",
    "message_direction": "Receive",
    "context_confidence": "medium",
    "file": "gamemode\\core\\libs\\thirdparty\\sh_netstream2.lua",
    "line": 102,
    "realm": "shared",
    "framework_layer": "framework"
  },
  {
    "type": "net_read_primitive",
    "method_name": "ReadUInt",
    "raw_args": "32",
    "message_name": "NetStreamDS",
    "message_direction": "Receive",
    "context_confidence": "medium",
    "file": "gamemode\\core\\libs\\thirdparty\\sh_netstream2.lua",
    "line": 103,
    "realm": "shared",
    "framework_layer": "framework"
  },
  {
    "type": "net_read_complex_or_bulk",
    "method_name": "ReadData",
    "raw_args": "NS_DS_LENGTH",
    "message_name": "NetStreamDS",
    "message_direction": "Receive",
    "context_confidence": "medium",
    "file": "gamemode\\core\\libs\\thirdparty\\sh_netstream2.lua",
    "line": 104,
    "realm": "shared",
    "framework_layer": "framework"
  },
  {
    "type": "net_read_primitive",
    "method_name": "ReadString",
    "raw_args": "",
    "message_name": "NetStreamDS",
    "message_direction": "Receive",
    "context_confidence": "medium",
    "file": "gamemode\\core\\libs\\thirdparty\\sh_netstream2.lua",
    "line": 146,
    "realm": "shared",
    "framework_layer": "framework"
  },
  {
    "type": "net_read_primitive",
    "method_name": "ReadUInt",
    "raw_args": "32",
    "message_name": "NetStreamDS",
    "message_direction": "Receive",
    "context_confidence": "medium",
    "file": "gamemode\\core\\libs\\thirdparty\\sh_netstream2.lua",
    "line": 147,
    "realm": "shared",
    "framework_layer": "framework"
  },
  {
    "type": "net_read_complex_or_bulk",
    "method_name": "ReadData",
    "raw_args": "NS_DS_LENGTH",
    "message_name": "NetStreamDS",
    "message_direction": "Receive",
    "context_confidence": "medium",
    "file": "gamemode\\core\\libs\\thirdparty\\sh_netstream2.lua",
    "line": 148,
    "realm": "shared",
    "framework_layer": "framework"
  },
  {
    "type": "net_read_other",
    "method_name": "ReadType",
    "raw_args": "",
    "message_name": "nutInventoryData",
    "message_direction": "Receive",
    "context_confidence": "medium",
    "file": "gamemode\\core\\meta\\inventory\\cl_base_inventory.lua",
    "line": 4,
    "realm": "client",
    "framework_layer": "framework"
  },
  {
    "type": "net_read_primitive",
    "method_name": "ReadString",
    "raw_args": "",
    "message_name": "nutInventoryData",
    "message_direction": "Receive",
    "context_confidence": "medium",
    "file": "gamemode\\core\\meta\\inventory\\cl_base_inventory.lua",
    "line": 5,
    "realm": "client",
    "framework_layer": "framework"
  },
  {
    "type": "net_read_other",
    "method_name": "ReadType",
    "raw_args": "",
    "message_name": "nutInventoryData",
    "message_direction": "Receive",
    "context_confidence": "medium",
    "file": "gamemode\\core\\meta\\inventory\\cl_base_inventory.lua",
    "line": 6,
    "realm": "client",
    "framework_layer": "framework"
  },
  {
    "type": "net_read_other",
    "method_name": "ReadType",
    "raw_args": "",
    "message_name": "nutInventoryInit",
    "message_direction": "Receive",
    "context_confidence": "medium",
    "file": "gamemode\\core\\meta\\inventory\\cl_base_inventory.lua",
    "line": 21,
    "realm": "client",
    "framework_layer": "framework"
  },
  {
    "type": "net_read_primitive",
    "method_name": "ReadString",
    "raw_args": "",
    "message_name": "nutInventoryInit",
    "message_direction": "Receive",
    "context_confidence": "medium",
    "file": "gamemode\\core\\meta\\inventory\\cl_base_inventory.lua",
    "line": 22,
    "realm": "client",
    "framework_layer": "framework"
  },
  {
    "type": "net_read_complex_or_bulk",
    "method_name": "ReadTable",
    "raw_args": "",
    "message_name": "nutInventoryInit",
    "message_direction": "Receive",
    "context_confidence": "medium",
    "file": "gamemode\\core\\meta\\inventory\\cl_base_inventory.lua",
    "line": 23,
    "realm": "client",
    "framework_layer": "framework"
  },
  {
    "type": "net_read_primitive",
    "method_name": "ReadUInt",
    "raw_args": "32",
    "message_name": "nutInventoryInit",
    "message_direction": "Receive",
    "context_confidence": "medium",
    "file": "gamemode\\core\\meta\\inventory\\cl_base_inventory.lua",
    "line": 29,
    "realm": "client",
    "framework_layer": "framework"
  },
  {
    "type": "net_read_primitive",
    "method_name": "ReadUInt",
    "raw_args": "32",
    "message_name": "nutInventoryInit",
    "message_direction": "Receive",
    "context_confidence": "medium",
    "file": "gamemode\\core\\meta\\inventory\\cl_base_inventory.lua",
    "line": 31,
    "realm": "client",
    "framework_layer": "framework"
  },
  {
    "type": "net_read_primitive",
    "method_name": "ReadString",
    "raw_args": "",
    "message_name": "nutInventoryInit",
    "message_direction": "Receive",
    "context_confidence": "medium",
    "file": "gamemode\\core\\meta\\inventory\\cl_base_inventory.lua",
    "line": 31,
    "realm": "client",
    "framework_layer": "framework"
  },
  {
    "type": "net_read_complex_or_bulk",
    "method_name": "ReadTable",
    "raw_args": "",
    "message_name": "nutInventoryInit",
    "message_direction": "Receive",
    "context_confidence": "medium",
    "file": "gamemode\\core\\meta\\inventory\\cl_base_inventory.lua",
    "line": 31,
    "realm": "client",
    "framework_layer": "framework"
  },
  {
    "type": "net_read_primitive",
    "method_name": "ReadUInt",
    "raw_args": "32",
    "message_name": "nutInventoryInit",
    "message_direction": "Receive",
    "context_confidence": "medium",
    "file": "gamemode\\core\\meta\\inventory\\cl_base_inventory.lua",
    "line": 31,
    "realm": "client",
    "framework_layer": "framework"
  },
  {
    "type": "net_read_primitive",
    "method_name": "ReadUInt",
    "raw_args": "32",
    "message_name": "nutInventoryAdd",
    "message_direction": "Receive",
    "context_confidence": "medium",
    "file": "gamemode\\core\\meta\\inventory\\cl_base_inventory.lua",
    "line": 57,
    "realm": "client",
    "framework_layer": "framework"
  },
  {
    "type": "net_read_other",
    "method_name": "ReadType",
    "raw_args": "",
    "message_name": "nutInventoryAdd",
    "message_direction": "Receive",
    "context_confidence": "medium",
    "file": "gamemode\\core\\meta\\inventory\\cl_base_inventory.lua",
    "line": 58,
    "realm": "client",
    "framework_layer": "framework"
  },
  {
    "type": "net_read_primitive",
    "method_name": "ReadUInt",
    "raw_args": "32",
    "message_name": "nutInventoryRemove",
    "message_direction": "Receive",
    "context_confidence": "medium",
    "file": "gamemode\\core\\meta\\inventory\\cl_base_inventory.lua",
    "line": 68,
    "realm": "client",
    "framework_layer": "framework"
  },
  {
    "type": "net_read_other",
    "method_name": "ReadType",
    "raw_args": "",
    "message_name": "nutInventoryRemove",
    "message_direction": "Receive",
    "context_confidence": "medium",
    "file": "gamemode\\core\\meta\\inventory\\cl_base_inventory.lua",
    "line": 69,
    "realm": "client",
    "framework_layer": "framework"
  },
  {
    "type": "net_read_other",
    "method_name": "ReadType",
    "raw_args": "",
    "message_name": "nutInventoryDelete",
    "message_direction": "Receive",
    "context_confidence": "medium",
    "file": "gamemode\\core\\meta\\inventory\\cl_base_inventory.lua",
    "line": 80,
    "realm": "client",
    "framework_layer": "framework"
  },
  {
    "type": "net_read_primitive",
    "method_name": "ReadUInt",
    "raw_args": "32",
    "message_name": "nutTransferItem",
    "message_direction": "Receive",
    "context_confidence": "medium",
    "file": "plugins\\gridinv\\sv_transfer.lua",
    "line": 230,
    "realm": "server",
    "framework_layer": "framework"
  },
  {
    "type": "net_read_primitive",
    "method_name": "ReadUInt",
    "raw_args": "32",
    "message_name": "nutTransferItem",
    "message_direction": "Receive",
    "context_confidence": "medium",
    "file": "plugins\\gridinv\\sv_transfer.lua",
    "line": 231,
    "realm": "server",
    "framework_layer": "framework"
  },
  {
    "type": "net_read_primitive",
    "method_name": "ReadUInt",
    "raw_args": "32",
    "message_name": "nutTransferItem",
    "message_direction": "Receive",
    "context_confidence": "medium",
    "file": "plugins\\gridinv\\sv_transfer.lua",
    "line": 232,
    "realm": "server",
    "framework_layer": "framework"
  },
  {
    "type": "net_read_other",
    "method_name": "ReadType",
    "raw_args": "",
    "message_name": "nutTransferItem",
    "message_direction": "Receive",
    "context_confidence": "medium",
    "file": "plugins\\gridinv\\sv_transfer.lua",
    "line": 233,
    "realm": "server",
    "framework_layer": "framework"
  },
  {
    "type": "net_read_primitive",
    "method_name": "ReadBool",
    "raw_args": "",
    "message_name": "nutTransferItem",
    "message_direction": "Receive",
    "context_confidence": "medium",
    "file": "plugins\\gridinv\\sv_transfer.lua",
    "line": 234,
    "realm": "server",
    "framework_layer": "framework"
  },
  {
    "type": "net_read_primitive",
    "method_name": "ReadUInt",
    "raw_args": "32",
    "message_name": "nutCharList",
    "message_direction": "Receive",
    "context_confidence": "medium",
    "file": "plugins\\multichar\\cl_networking.lua",
    "line": 3,
    "realm": "client",
    "framework_layer": "framework"
  },
  {
    "type": "net_read_primitive",
    "method_name": "ReadUInt",
    "raw_args": "32",
    "message_name": "nutCharList",
    "message_direction": "Receive",
    "context_confidence": "medium",
    "file": "plugins\\multichar\\cl_networking.lua",
    "line": 5,
    "realm": "client",
    "framework_layer": "framework"
  },
  {
    "type": "net_read_primitive",
    "method_name": "ReadString",
    "raw_args": "",
    "message_name": "nutCharChoose",
    "message_direction": "Receive",
    "context_confidence": "medium",
    "file": "plugins\\multichar\\sh_plugin.lua",
    "line": 38,
    "realm": "shared",
    "framework_layer": "framework"
  },
  {
    "type": "net_read_primitive",
    "method_name": "ReadUInt",
    "raw_args": "32",
    "message_name": "nutCharCreate",
    "message_direction": "Receive",
    "context_confidence": "medium",
    "file": "plugins\\multichar\\sh_plugin.lua",
    "line": 76,
    "realm": "shared",
    "framework_layer": "framework"
  },
  {
    "type": "net_read_primitive",
    "method_name": "ReadString",
    "raw_args": "",
    "message_name": "nutCharCreate",
    "message_direction": "Receive",
    "context_confidence": "medium",
    "file": "plugins\\multichar\\sh_plugin.lua",
    "line": 77,
    "realm": "shared",
    "framework_layer": "framework"
  },
  {
    "type": "net_read_primitive",
    "method_name": "ReadUInt",
    "raw_args": "32",
    "message_name": "nutCharChoose",
    "message_direction": "Start",
    "context_confidence": "medium",
    "file": "plugins\\multichar\\sv_networking.lua",
    "line": 16,
    "realm": "server",
    "framework_layer": "framework"
  },
  {
    "type": "net_read_primitive",
    "method_name": "ReadUInt",
    "raw_args": "32",
    "message_name": "nutCharCreate",
    "message_direction": "Start",
    "context_confidence": "medium",
    "file": "plugins\\multichar\\sv_networking.lua",
    "line": 52,
    "realm": "server",
    "framework_layer": "framework"
  },
  {
    "type": "net_read_primitive",
    "method_name": "ReadString",
    "raw_args": "",
    "message_name": "nutCharCreate",
    "message_direction": "Start",
    "context_confidence": "medium",
    "file": "plugins\\multichar\\sv_networking.lua",
    "line": 55,
    "realm": "server",
    "framework_layer": "framework"
  },
  {
    "type": "net_read_other",
    "method_name": "ReadType",
    "raw_args": "",
    "message_name": "nutCharCreate",
    "message_direction": "Start",
    "context_confidence": "medium",
    "file": "plugins\\multichar\\sv_networking.lua",
    "line": 55,
    "realm": "server",
    "framework_layer": "framework"
  },
  {
    "type": "net_read_primitive",
    "method_name": "ReadUInt",
    "raw_args": "32",
    "message_name": "nutCharDelete",
    "message_direction": "Receive",
    "context_confidence": "medium",
    "file": "plugins\\multichar\\sv_networking.lua",
    "line": 111,
    "realm": "server",
    "framework_layer": "framework"
  },
  {
    "type": "net_read_entity_ref",
    "method_name": "ReadEntity",
    "raw_args": "",
    "message_name": "nutPACPartAdd",
    "message_direction": "Receive",
    "context_confidence": "medium",
    "file": "plugins\\pac\\cl_parts.lua",
    "line": 60,
    "realm": "client",
    "framework_layer": "framework"
  },
  {
    "type": "net_read_primitive",
    "method_name": "ReadString",
    "raw_args": "",
    "message_name": "nutPACPartAdd",
    "message_direction": "Receive",
    "context_confidence": "medium",
    "file": "plugins\\pac\\cl_parts.lua",
    "line": 61,
    "realm": "client",
    "framework_layer": "framework"
  },
  {
    "type": "net_read_entity_ref",
    "method_name": "ReadEntity",
    "raw_args": "",
    "message_name": "nutPACPartRemove",
    "message_direction": "Receive",
    "context_confidence": "medium",
    "file": "plugins\\pac\\cl_parts.lua",
    "line": 68,
    "realm": "client",
    "framework_layer": "framework"
  },
  {
    "type": "net_read_primitive",
    "method_name": "ReadString",
    "raw_args": "",
    "message_name": "nutPACPartRemove",
    "message_direction": "Receive",
    "context_confidence": "medium",
    "file": "plugins\\pac\\cl_parts.lua",
    "line": 69,
    "realm": "client",
    "framework_layer": "framework"
  },
  {
    "type": "net_read_entity_ref",
    "method_name": "ReadEntity",
    "raw_args": "",
    "message_name": "nutPACPartReset",
    "message_direction": "Receive",
    "context_confidence": "medium",
    "file": "plugins\\pac\\cl_parts.lua",
    "line": 76,
    "realm": "client",
    "framework_layer": "framework"
  },
  {
    "type": "net_read_entity_ref",
    "method_name": "ReadEntity",
    "raw_args": "",
    "message_name": "nutStorageUnlock",
    "message_direction": "Receive",
    "context_confidence": "medium",
    "file": "plugins\\storage\\cl_networking.lua",
    "line": 2,
    "realm": "client",
    "framework_layer": "framework"
  },
  {
    "type": "net_read_entity_ref",
    "method_name": "ReadEntity",
    "raw_args": "",
    "message_name": "nutStorageOpen",
    "message_direction": "Receive",
    "context_confidence": "medium",
    "file": "plugins\\storage\\cl_networking.lua",
    "line": 7,
    "realm": "client",
    "framework_layer": "framework"
  },
  {
    "type": "net_read_primitive",
    "method_name": "ReadString",
    "raw_args": "",
    "message_name": "nutStorageUnlock",
    "message_direction": "Receive",
    "context_confidence": "medium",
    "file": "plugins\\storage\\sv_networking.lua",
    "line": 24,
    "realm": "server",
    "framework_layer": "framework"
  },
  {
    "type": "net_read_primitive",
    "method_name": "ReadUInt",
    "raw_args": "32",
    "message_name": "nutStorageTransfer",
    "message_direction": "Receive",
    "context_confidence": "medium",
    "file": "plugins\\storage\\sv_networking.lua",
    "line": 44,
    "realm": "server",
    "framework_layer": "framework"
  },
  {
    "type": "net_read_entity_ref",
    "method_name": "ReadEntity",
    "raw_args": "",
    "message_name": "nutVendorSync",
    "message_direction": "Receive",
    "context_confidence": "medium",
    "file": "plugins\\vendor\\cl_networking.lua",
    "line": 10,
    "realm": "client",
    "framework_layer": "framework"
  },
  {
    "type": "net_read_primitive",
    "method_name": "ReadInt",
    "raw_args": "32",
    "message_name": "nutVendorSync",
    "message_direction": "Receive",
    "context_confidence": "medium",
    "file": "plugins\\vendor\\cl_networking.lua",
    "line": 13,
    "realm": "client",
    "framework_layer": "framework"
  },
  {
    "type": "net_read_primitive",
    "method_name": "ReadUInt",
    "raw_args": "16",
    "message_name": "nutVendorSync",
    "message_direction": "Receive",
    "context_confidence": "medium",
    "file": "plugins\\vendor\\cl_networking.lua",
    "line": 18,
    "realm": "client",
    "framework_layer": "framework"
  },
  {
    "type": "net_read_primitive",
    "method_name": "ReadString",
    "raw_args": "",
    "message_name": "nutVendorSync",
    "message_direction": "Receive",
    "context_confidence": "medium",
    "file": "plugins\\vendor\\cl_networking.lua",
    "line": 20,
    "realm": "client",
    "framework_layer": "framework"
  },
  {
    "type": "net_read_primitive",
    "method_name": "ReadInt",
    "raw_args": "32",
    "message_name": "nutVendorSync",
    "message_direction": "Receive",
    "context_confidence": "medium",
    "file": "plugins\\vendor\\cl_networking.lua",
    "line": 21,
    "realm": "client",
    "framework_layer": "framework"
  },
  {
    "type": "net_read_primitive",
    "method_name": "ReadInt",
    "raw_args": "32",
    "message_name": "nutVendorSync",
    "message_direction": "Receive",
    "context_confidence": "medium",
    "file": "plugins\\vendor\\cl_networking.lua",
    "line": 22,
    "realm": "client",
    "framework_layer": "framework"
  },
  {
    "type": "net_read_primitive",
    "method_name": "ReadInt",
    "raw_args": "32",
    "message_name": "nutVendorSync",
    "message_direction": "Receive",
    "context_confidence": "medium",
    "file": "plugins\\vendor\\cl_networking.lua",
    "line": 23,
    "realm": "client",
    "framework_layer": "framework"
  },
  {
    "type": "net_read_primitive",
    "method_name": "ReadInt",
    "raw_args": "8",
    "message_name": "nutVendorSync",
    "message_direction": "Receive",
    "context_confidence": "medium",
    "file": "plugins\\vendor\\cl_networking.lua",
    "line": 24,
    "realm": "client",
    "framework_layer": "framework"
  },
  {
    "type": "net_read_entity_ref",
    "method_name": "ReadEntity",
    "raw_args": "",
    "message_name": "nutVendorOpen",
    "message_direction": "Receive",
    "context_confidence": "medium",
    "file": "plugins\\vendor\\cl_networking.lua",
    "line": 43,
    "realm": "client",
    "framework_layer": "framework"
  },
  {
    "type": "net_read_primitive",
    "method_name": "ReadInt",
    "raw_args": "32",
    "message_name": "nutVendorExit",
    "message_direction": "Receive",
    "context_confidence": "medium",
    "file": "plugins\\vendor\\cl_networking.lua",
    "line": 56,
    "realm": "client",
    "framework_layer": "framework"
  },
  {
    "type": "net_read_primitive",
    "method_name": "ReadString",
    "raw_args": "",
    "message_name": "nutVendorExit",
    "message_direction": "Receive",
    "context_confidence": "medium",
    "file": "plugins\\vendor\\cl_networking.lua",
    "line": 63,
    "realm": "client",
    "framework_layer": "framework"
  },
  {
    "type": "net_read_primitive",
    "method_name": "ReadInt",
    "raw_args": "32",
    "message_name": "nutVendorExit",
    "message_direction": "Receive",
    "context_confidence": "medium",
    "file": "plugins\\vendor\\cl_networking.lua",
    "line": 64,
    "realm": "client",
    "framework_layer": "framework"
  },
  {
    "type": "net_read_primitive",
    "method_name": "ReadString",
    "raw_args": "",
    "message_name": "nutVendorExit",
    "message_direction": "Receive",
    "context_confidence": "medium",
    "file": "plugins\\vendor\\cl_networking.lua",
    "line": 74,
    "realm": "client",
    "framework_layer": "framework"
  },
  {
    "type": "net_read_primitive",
    "method_name": "ReadInt",
    "raw_args": "8",
    "message_name": "nutVendorExit",
    "message_direction": "Receive",
    "context_confidence": "medium",
    "file": "plugins\\vendor\\cl_networking.lua",
    "line": 75,
    "realm": "client",
    "framework_layer": "framework"
  },
  {
    "type": "net_read_primitive",
    "method_name": "ReadString",
    "raw_args": "",
    "message_name": "nutVendorExit",
    "message_direction": "Receive",
    "context_confidence": "medium",
    "file": "plugins\\vendor\\cl_networking.lua",
    "line": 85,
    "realm": "client",
    "framework_layer": "framework"
  },
  {
    "type": "net_read_primitive",
    "method_name": "ReadUInt",
    "raw_args": "32",
    "message_name": "nutVendorExit",
    "message_direction": "Receive",
    "context_confidence": "medium",
    "file": "plugins\\vendor\\cl_networking.lua",
    "line": 86,
    "realm": "client",
    "framework_layer": "framework"
  },
  {
    "type": "net_read_primitive",
    "method_name": "ReadString",
    "raw_args": "",
    "message_name": "nutVendorExit",
    "message_direction": "Receive",
    "context_confidence": "medium",
    "file": "plugins\\vendor\\cl_networking.lua",
    "line": 95,
    "realm": "client",
    "framework_layer": "framework"
  },
  {
    "type": "net_read_primitive",
    "method_name": "ReadUInt",
    "raw_args": "32",
    "message_name": "nutVendorExit",
    "message_direction": "Receive",
    "context_confidence": "medium",
    "file": "plugins\\vendor\\cl_networking.lua",
    "line": 96,
    "realm": "client",
    "framework_layer": "framework"
  },
  {
    "type": "net_read_primitive",
    "method_name": "ReadUInt",
    "raw_args": "8",
    "message_name": "nutVendorExit",
    "message_direction": "Receive",
    "context_confidence": "medium",
    "file": "plugins\\vendor\\cl_networking.lua",
    "line": 106,
    "realm": "client",
    "framework_layer": "framework"
  },
  {
    "type": "net_read_primitive",
    "method_name": "ReadBool",
    "raw_args": "",
    "message_name": "nutVendorExit",
    "message_direction": "Receive",
    "context_confidence": "medium",
    "file": "plugins\\vendor\\cl_networking.lua",
    "line": 107,
    "realm": "client",
    "framework_layer": "framework"
  },
  {
    "type": "net_read_primitive",
    "method_name": "ReadUInt",
    "raw_args": "8",
    "message_name": "nutVendorExit",
    "message_direction": "Receive",
    "context_confidence": "medium",
    "file": "plugins\\vendor\\cl_networking.lua",
    "line": 119,
    "realm": "client",
    "framework_layer": "framework"
  },
  {
    "type": "net_read_primitive",
    "method_name": "ReadBool",
    "raw_args": "",
    "message_name": "nutVendorExit",
    "message_direction": "Receive",
    "context_confidence": "medium",
    "file": "plugins\\vendor\\cl_networking.lua",
    "line": 120,
    "realm": "client",
    "framework_layer": "framework"
  },
  {
    "type": "net_read_primitive",
    "method_name": "ReadString",
    "raw_args": "",
    "message_name": "nutVendorEdit",
    "message_direction": "Receive",
    "context_confidence": "medium",
    "file": "plugins\\vendor\\cl_networking.lua",
    "line": 132,
    "realm": "client",
    "framework_layer": "framework"
  },
  {
    "type": "net_read_primitive",
    "method_name": "ReadUInt",
    "raw_args": "8",
    "message_name": "nutVendorFaction",
    "message_direction": "Receive",
    "context_confidence": "medium",
    "file": "plugins\\vendor\\cl_networking.lua",
    "line": 141,
    "realm": "client",
    "framework_layer": "framework"
  },
  {
    "type": "net_read_primitive",
    "method_name": "ReadString",
    "raw_args": "",
    "message_name": null,
    "message_direction": null,
    "context_confidence": "low",
    "file": "plugins\\vendor\\sv_editor.lua",
    "line": 4,
    "realm": "server",
    "framework_layer": "framework"
  },
  {
    "type": "net_read_primitive",
    "method_name": "ReadString",
    "raw_args": "",
    "message_name": null,
    "message_direction": null,
    "context_confidence": "low",
    "file": "plugins\\vendor\\sv_editor.lua",
    "line": 9,
    "realm": "server",
    "framework_layer": "framework"
  },
  {
    "type": "net_read_primitive",
    "method_name": "ReadBool",
    "raw_args": "",
    "message_name": null,
    "message_direction": null,
    "context_confidence": "low",
    "file": "plugins\\vendor\\sv_editor.lua",
    "line": 14,
    "realm": "server",
    "framework_layer": "framework"
  },
  {
    "type": "net_read_primitive",
    "method_name": "ReadString",
    "raw_args": "",
    "message_name": null,
    "message_direction": null,
    "context_confidence": "low",
    "file": "plugins\\vendor\\sv_editor.lua",
    "line": 19,
    "realm": "server",
    "framework_layer": "framework"
  },
  {
    "type": "net_read_primitive",
    "method_name": "ReadInt",
    "raw_args": "8",
    "message_name": null,
    "message_direction": null,
    "context_confidence": "low",
    "file": "plugins\\vendor\\sv_editor.lua",
    "line": 20,
    "realm": "server",
    "framework_layer": "framework"
  },
  {
    "type": "net_read_primitive",
    "method_name": "ReadString",
    "raw_args": "",
    "message_name": null,
    "message_direction": null,
    "context_confidence": "low",
    "file": "plugins\\vendor\\sv_editor.lua",
    "line": 26,
    "realm": "server",
    "framework_layer": "framework"
  },
  {
    "type": "net_read_primitive",
    "method_name": "ReadInt",
    "raw_args": "32",
    "message_name": null,
    "message_direction": null,
    "context_confidence": "low",
    "file": "plugins\\vendor\\sv_editor.lua",
    "line": 27,
    "realm": "server",
    "framework_layer": "framework"
  },
  {
    "type": "net_read_primitive",
    "method_name": "ReadString",
    "raw_args": "",
    "message_name": null,
    "message_direction": null,
    "context_confidence": "low",
    "file": "plugins\\vendor\\sv_editor.lua",
    "line": 33,
    "realm": "server",
    "framework_layer": "framework"
  },
  {
    "type": "net_read_primitive",
    "method_name": "ReadString",
    "raw_args": "",
    "message_name": null,
    "message_direction": null,
    "context_confidence": "low",
    "file": "plugins\\vendor\\sv_editor.lua",
    "line": 38,
    "realm": "server",
    "framework_layer": "framework"
  },
  {
    "type": "net_read_primitive",
    "method_name": "ReadUInt",
    "raw_args": "32",
    "message_name": null,
    "message_direction": null,
    "context_confidence": "low",
    "file": "plugins\\vendor\\sv_editor.lua",
    "line": 39,
    "realm": "server",
    "framework_layer": "framework"
  },
  {
    "type": "net_read_primitive",
    "method_name": "ReadString",
    "raw_args": "",
    "message_name": null,
    "message_direction": null,
    "context_confidence": "low",
    "file": "plugins\\vendor\\sv_editor.lua",
    "line": 44,
    "realm": "server",
    "framework_layer": "framework"
  },
  {
    "type": "net_read_primitive",
    "method_name": "ReadUInt",
    "raw_args": "32",
    "message_name": null,
    "message_direction": null,
    "context_confidence": "low",
    "file": "plugins\\vendor\\sv_editor.lua",
    "line": 45,
    "realm": "server",
    "framework_layer": "framework"
  },
  {
    "type": "net_read_primitive",
    "method_name": "ReadUInt",
    "raw_args": "8",
    "message_name": null,
    "message_direction": null,
    "context_confidence": "low",
    "file": "plugins\\vendor\\sv_editor.lua",
    "line": 50,
    "realm": "server",
    "framework_layer": "framework"
  },
  {
    "type": "net_read_primitive",
    "method_name": "ReadBool",
    "raw_args": "",
    "message_name": null,
    "message_direction": null,
    "context_confidence": "low",
    "file": "plugins\\vendor\\sv_editor.lua",
    "line": 51,
    "realm": "server",
    "framework_layer": "framework"
  },
  {
    "type": "net_read_primitive",
    "method_name": "ReadUInt",
    "raw_args": "8",
    "message_name": null,
    "message_direction": null,
    "context_confidence": "low",
    "file": "plugins\\vendor\\sv_editor.lua",
    "line": 56,
    "realm": "server",
    "framework_layer": "framework"
  },
  {
    "type": "net_read_primitive",
    "method_name": "ReadBool",
    "raw_args": "",
    "message_name": null,
    "message_direction": null,
    "context_confidence": "low",
    "file": "plugins\\vendor\\sv_editor.lua",
    "line": 57,
    "realm": "server",
    "framework_layer": "framework"
  },
  {
    "type": "net_read_primitive",
    "method_name": "ReadString",
    "raw_args": "",
    "message_name": null,
    "message_direction": null,
    "context_confidence": "low",
    "file": "plugins\\vendor\\sv_editor.lua",
    "line": 62,
    "realm": "server",
    "framework_layer": "framework"
  },
  {
    "type": "net_read_primitive",
    "method_name": "ReadBool",
    "raw_args": "",
    "message_name": null,
    "message_direction": null,
    "context_confidence": "low",
    "file": "plugins\\vendor\\sv_editor.lua",
    "line": 67,
    "realm": "server",
    "framework_layer": "framework"
  },
  {
    "type": "net_read_primitive",
    "method_name": "ReadUInt",
    "raw_args": "32",
    "message_name": null,
    "message_direction": null,
    "context_confidence": "low",
    "file": "plugins\\vendor\\sv_editor.lua",
    "line": 76,
    "realm": "server",
    "framework_layer": "framework"
  },
  {
    "type": "net_read_primitive",
    "method_name": "ReadFloat",
    "raw_args": "",
    "message_name": null,
    "message_direction": null,
    "context_confidence": "low",
    "file": "plugins\\vendor\\sv_editor.lua",
    "line": 81,
    "realm": "server",
    "framework_layer": "framework"
  },
  {
    "type": "net_read_primitive",
    "method_name": "ReadString",
    "raw_args": "",
    "message_name": "nutVendorEdit",
    "message_direction": "Receive",
    "context_confidence": "medium",
    "file": "plugins\\vendor\\sv_networking.lua",
    "line": 25,
    "realm": "server",
    "framework_layer": "framework"
  },
  {
    "type": "net_read_primitive",
    "method_name": "ReadString",
    "raw_args": "",
    "message_name": "nutVendorTrade",
    "message_direction": "Receive",
    "context_confidence": "medium",
    "file": "plugins\\vendor\\sv_networking.lua",
    "line": 37,
    "realm": "server",
    "framework_layer": "framework"
  },
  {
    "type": "net_read_primitive",
    "method_name": "ReadBool",
    "raw_args": "",
    "message_name": "nutVendorTrade",
    "message_direction": "Receive",
    "context_confidence": "medium",
    "file": "plugins\\vendor\\sv_networking.lua",
    "line": 38,
    "realm": "server",
    "framework_layer": "framework"
  }
]